intelab_python_tool/__init__.py
intelab_python_tool/algorithm/__init__.py
intelab_python_tool/algorithm/aftertreat/__init__.py
intelab_python_tool/algorithm/pretreat/__init__.py
intelab_python_tool/tools/__init__.py
intelab_python_tool/tools/datatype.py
intelab_python_tool/tools/time.py
intelab_python_tool/tools/Office/__init__.py
intelab_python_tool/tools/Office/excel.py
intelab_python_tool/tools/Office/ppt.py
intelab_python_tool/tools/Office/word.py
intelab_python_tool/tools/Web/__init__.py
intelab_python_tool/tools/Web/flaskAPI.py
intelab_python_tool/tools/alarm/__init__.py
intelab_python_tool/tools/alarm/ding.py
intelab_python_tool/tools/alarm/email.py
intelab_python_tool/tools/alarm/fly.py
intelab_python_tool/tools/connect/AliyunOss.py
intelab_python_tool/tools/connect/Influxdb.py
intelab_python_tool/tools/connect/Mysql.py
intelab_python_tool/tools/connect/Rabbitmq.py
intelab_python_tool/tools/connect/Redis.py
intelab_python_tool/tools/connect/Tdengine.py
intelab_python_tool/tools/connect/__init__.py
intelab_python_tool/tools/log/__init__.py
intelab_python_tool/tools/log/timeroatingfilehandler.py
intelab_python_tool/tools/program/__init__.py
intelab_python_tool/tools/program/template_ilab1.py
intelab_python_tool/tools/program/templates.py
intelab_python_tool-0.1.5.dist-info/LICENSE
intelab_python_tool-0.1.5.dist-info/METADATA
intelab_python_tool-0.1.5.dist-info/WHEEL
intelab_python_tool-0.1.5.dist-info/top_level.txt
intelab_python_tool-0.1.5.dist-info/RECORD
